[{"transaction_id":"1639433003","post_id":"1639415874","seller_id":"80","seller_username":"test","buyer_id":"80","buyer_username":"test","product_name":"","amount":"0","price":"0","address":"test","zip_code":"0","city":"test","collection_day":"2021-12-15","phone_number":"0","time_slot":"8:00 - 10:00"},{"transaction_id":"1639433407","post_id":"1639415874","seller_id":"80","seller_username":"test","buyer_id":"80","buyer_username":"test","product_name":"","amount":"0","price":"0","address":"test","zip_code":"0","city":"test","collection_day":"2021-12-15","phone_number":"0","time_slot":"8:00 - 10:00"},{"transaction_id":"1639433437","post_id":"1639415874","seller_id":"80","seller_username":"test","buyer_id":"80","buyer_username":"test","product_name":"","amount":"0","price":"0","address":"test","zip_code":"0","city":"test","collection_day":"2021-12-15","phone_number":"0","time_slot":"8:00 - 10:00"},{"transaction_id":"1639433537","post_id":"1639415874","seller_id":"80","seller_username":"test","buyer_id":"80","buyer_username":"test","product_name":"","amount":"0","price":"0","address":"test","zip_code":"0","city":"test","collection_day":"2021-12-15","phone_number":"0","time_slot":"8:00 - 10:00"},{"transaction_id":"1639433593","post_id":"1639415874","seller_id":"80","seller_username":"test","buyer_id":"80","buyer_username":"test","product_name":"","amount":"0","price":"0","address":"test","zip_code":"0","city":"test","collection_day":"2021-12-15","phone_number":"0","time_slot":"8:00 - 10:00"},{"transaction_id":"1639433638","post_id":"1639415874","seller_id":"80","seller_username":"test","buyer_id":"80","buyer_username":"test","product_name":"","amount":"0","price":"0","address":"test","zip_code":"0","city":"test","collection_day":"2021-12-15","phone_number":"0","time_slot":"8:00 - 10:00"},{"transaction_id":"1639434347","post_id":"1639415874","seller_id":"80","seller_username":"test","buyer_id":"80","buyer_username":"test","product_name":"","amount":"0","price":"0","address":"test","zip_code":"0","city":"test","collection_day":"2021-12-15","phone_number":"0","time_slot":"8:00 - 10:00"},{"transaction_id":"1639434684","post_id":"1639415874","seller_id":"80","seller_username":"test","buyer_id":"80","buyer_username":"test","product_name":"","amount":"0","price":"0","address":"test","zip_code":"0","city":"test","collection_day":"2021-12-15","phone_number":"0","time_slot":"8:00 - 10:00"},{"transaction_id":"1639434728","post_id":"1639415874","seller_id":"80","seller_username":"test","buyer_id":"80","buyer_username":"test","product_name":"","amount":"0","price":"0","address":"test","zip_code":"0","city":"test","collection_day":"2021-12-15","phone_number":"0","time_slot":"8:00 - 10:00"},{"transaction_id":"1639434945","post_id":"1639415874","seller_id":"80","seller_username":"test","buyer_id":"80","buyer_username":"test","product_name":"","amount":"0","price":"0","address":"test","zip_code":"0","city":"test","collection_day":"2021-12-15","phone_number":"0","time_slot":"8:00 - 10:00"},{"transaction_id":"1639434951","post_id":"1639415874","seller_id":"80","seller_username":"test","buyer_id":"80","buyer_username":"test","product_name":"","amount":"0","price":"0","address":"test","zip_code":"0","city":"test","collection_day":"2021-12-15","phone_number":"0","time_slot":"8:00 - 10:00"},{"transaction_id":"1639435002","post_id":"1639415874","seller_id":"80","seller_username":"test","buyer_id":"80","buyer_username":"test","product_name":"","amount":"0","price":"0","address":"test","zip_code":"0","city":"test","collection_day":"2021-12-15","phone_number":"0","time_slot":"8:00 - 10:00"},{"transaction_id":"1639435185","post_id":"1639415874","seller_id":"80","seller_username":"test","buyer_id":"80","buyer_username":"test","product_name":"","amount":"0","price":"0","address":"test","zip_code":"0","city":"test","collection_day":"2021-12-15","phone_number":"0","time_slot":"8:00 - 10:00"},{"transaction_id":"1639435482","post_id":"1639415874","seller_id":"80","seller_username":"test","buyer_id":"80","buyer_username":"test","product_name":"time slots","amount":"0","price":"0","address":"test","zip_code":"0","city":"test","collection_day":"2021-12-15","phone_number":"0","time_slot":"8:00 - 10:00"},{"transaction_id":"1639435826","post_id":"1639415874","seller_id":"80","seller_username":"test","buyer_id":"80","buyer_username":"test","product_name":"time slots","amount":"0","price":"0","address":"test","zip_code":"0","city":"test","collection_day":"2021-12-15","phone_number":"0","time_slot":"8:00 - 10:00"},{"transaction_id":"1639435916","post_id":"1639415874","seller_id":"80","seller_username":"test","buyer_id":"80","buyer_username":"test","product_name":"time slots","amount":"0","price":"0","address":"test","zip_code":"0","city":"test","collection_day":"2021-12-15","phone_number":"0","time_slot":"14:00 - 16:00"},{"transaction_id":"1639435943","post_id":"1639415874","seller_id":"80","seller_username":"test","buyer_id":"80","buyer_username":"test","product_name":"time slots","amount":"0","price":"0","address":"test","zip_code":"0","city":"test","collection_day":"2021-12-15","phone_number":"0","time_slot":"8:00 - 10:00"},{"transaction_id":"1639436355","post_id":"1639415874","seller_id":"80","seller_username":"test","buyer_id":"80","buyer_username":"test","product_name":"time slots","amount":"0","price":"0","address":"test","zip_code":"0","city":"test","collection_day":"2021-12-15","phone_number":"0","time_slot":"8:00 - 10:00"},{"transaction_id":"1639436511","post_id":"1639415874","seller_id":"80","seller_username":"test","buyer_id":"80","buyer_username":"test","product_name":"time slots","amount":"0","price":"0","address":"test","zip_code":"0","city":"test","collection_day":"2021-12-15","phone_number":"0","time_slot":"8:00 - 10:00"},{"transaction_id":"1639436525","post_id":"1639415874","seller_id":"80","seller_username":"test","buyer_id":"80","buyer_username":"test","product_name":"time slots","amount":"0","price":"0","address":"test","zip_code":"0","city":"test","collection_day":"2021-12-15","phone_number":"0","time_slot":"8:00 - 10:00"}]